pyrill_fs/__init__.py
pyrill_fs/__version__.py
pyrill_fs/base.py
pyrill_fs/exceptions.py
pyrill_fs/local.py
pyrill_fs/s3.py
pyrill_fs/hdfs/__init__.py
pyrill_fs/hdfs/client.py
pyrill_fs/hdfs/errors.py
pyrill_fs/hdfs/models.py
pyrill_fs/hdfs/webhdfs_api_spec.py
pyrill_fs-0.1.2.dist-info/LICENSE
pyrill_fs-0.1.2.dist-info/METADATA
pyrill_fs-0.1.2.dist-info/WHEEL
pyrill_fs-0.1.2.dist-info/top_level.txt
pyrill_fs-0.1.2.dist-info/zip-safe
pyrill_fs-0.1.2.dist-info/RECORD
